common_components/__init__.py
common_components/src/__init__.py
common_components/src/base_files_dir.py
common_components/src/controller.py
common_components/src/descriptions.py
common_components/src/projects_collection.py
common_components/src/pytest.py
common_components/src/test_project_files.py
common_components/trees/__init__.py
common_components/trees/env_and_deploy_files.py
common_components/trees/project_trees.py
common_components/trees/test_project_sample.py
common_components/trees/test_project_tree.py
py_init_structure-0.1.3.dist-info/LICENSE
py_init_structure-0.1.3.dist-info/METADATA
py_init_structure-0.1.3.dist-info/WHEEL
py_init_structure-0.1.3.dist-info/entry_points.txt
py_init_structure-0.1.3.dist-info/top_level.txt
py_init_structure-0.1.3.dist-info/RECORD
