Metadata-Version: 2.1
Name: py-init-structure
Version: 0.1.3
Summary: Creates structure of autotest project
Home-page: UNKNOWN
Author: Sergii Golovach
License: MIT
Platform: UNKNOWN
Classifier: Programming Language :: Python :: 3
Requires-Python: >=3.7.5
Requires-Dist: click (==7.1.2)
Requires-Dist: questionary (==1.8.0)
